{"__type__":"cc.SpriteAtlas","_spriteFrames":{"gongnengjihuo_00":{"__uuid__":"b9IfHcCfVC/6alvpI0lIFm"},"gongnengjihuo_01":{"__uuid__":"928M5s/zlExYzQrPhcm8Wa"},"gongnengjihuo_02":{"__uuid__":"21+xukGU5D4q9QQd1UQRze"},"gongnengjihuo_03":{"__uuid__":"5fgfVt+Y9B9IFhf8j06KLX"},"gongnengjihuo_04":{"__uuid__":"c0Q10techHYY4Jez6ppqIT"},"gongnengjihuo_05":{"__uuid__":"e5ywjhh81Gf5mDr4ERDpg2"},"gongnengjihuo_06":{"__uuid__":"93I1DufNROk7Ubd0p5+JHM"},"gongnengjihuo_07":{"__uuid__":"63MPtPc4BPnrn3ePfZzUOc"},"gongnengjihuo_08":{"__uuid__":"48KFlPDmhIAIyTcD4h+1gI"},"gongnengjihuo_09":{"__uuid__":"2fdSvoXbVAdaZ4lF6MWZEc"},"gongnengjihuo_10":{"__uuid__":"cfCkkXen9LE6gibh18YeGQ"},"guangquan_0000":{"__uuid__":"8edR6r7fJBipURR/3fkbO6"},"guangquan_0001":{"__uuid__":"b9nOIXu3BO24IVWrjrrb/v"},"guangquan_0002":{"__uuid__":"d9CKv9EklL3LNP/6tZiaa6"},"guangquan_0003":{"__uuid__":"8eMhkLtlVIKKHp0jD5vVnj"},"guangquan_0004":{"__uuid__":"a4yuxRd+5OjZhkczudIBgE"},"guangquan_0005":{"__uuid__":"f5/zqtfMBP15x7ZNx88pz1"},"guangquan_0006":{"__uuid__":"96gR8o5ppOYJ57gm0+D9P4"},"guangquan_0007":{"__uuid__":"748d+HFY9J9JP6CClOaROE"},"guangquan_0008":{"__uuid__":"19Y8b7IS1FZbezzGV4nFkw"},"guangquan_0009":{"__uuid__":"65V2Wqe4xG5Zq5x4MxwEn6"},"yindaojiantou_0000":{"__uuid__":"eby4ju7zBG/rC1fhmzSOdP"},"yindaojiantou_0001":{"__uuid__":"8crZY2v2NGWbLQTQ/4YN2Y"},"yindaojiantou_0002":{"__uuid__":"97W5eQPkBPN68sqrSUeppT"},"yindaojiantou_0003":{"__uuid__":"57v2lS9/1G5aEDbL4c8CIO"},"yindaojiantou_0004":{"__uuid__":"2ayS3XCllIB6igGAMFsHwA"}}}